django_uploads_app/__init__.py
django_uploads_app/admin.py
django_uploads_app/apps.py
django_uploads_app/base_models.py
django_uploads_app/exceptions.py
django_uploads_app/filters.py
django_uploads_app/forms.py
django_uploads_app/functions.py
django_uploads_app/managers.py
django_uploads_app/models.py
django_uploads_app/permissions.py
django_uploads_app/serializers.py
django_uploads_app/settings.py
django_uploads_app/signals.py
django_uploads_app/storage.py
django_uploads_app/tests.py
django_uploads_app/urls.py
django_uploads_app/utils.py
django_uploads_app/views.py
django_uploads_app/ftp/__init__.py
django_uploads_app/ftp/apps.py
django_uploads_app/ftp/settings.py
django_uploads_app/ftp/signals.py
django_uploads_app/ftp/tasks.py
django_uploads_app/ftp/utils.py
django_uploads_app/ftp/tests/__init__.py
django_uploads_app/ftp/tests/test_app.py
django_uploads_app/management/__init__.py
django_uploads_app/management/commands/__init__.py
django_uploads_app/management/commands/ftp_parse_all_user_files.py
django_uploads_app/migrations/0001_initial.py
django_uploads_app/migrations/__init__.py
django_uploads_app/templates/django_uploads_app/file_upload.html
django_uploads_app/templates/django_uploads_app/file_upload_success.html
django_uploads_app/templates/django_uploads_app/partials/form.html
django_uploads_app-0.8.0.dist-info/AUTHORS.rst
django_uploads_app-0.8.0.dist-info/LICENSE
django_uploads_app-0.8.0.dist-info/METADATA
django_uploads_app-0.8.0.dist-info/WHEEL
django_uploads_app-0.8.0.dist-info/top_level.txt
django_uploads_app-0.8.0.dist-info/RECORD
