Metadata-Version: 2.1
Name: django-uploads-app
Version: 0.8.0
Summary: Django uploads manager
Home-page: https://github.com/paiuolo/django-uploads-app
Author: pai
Author-email: paiuolo@gmail.com
License: MIT
Keywords: django-uploads-app
Platform: UNKNOWN
Classifier: Development Status :: 3 - Alpha
Classifier: Framework :: Django :: 1.11
Classifier: Framework :: Django :: 2.1
Classifier: Intended Audience :: Developers
Classifier: License :: OSI Approved :: BSD License
Classifier: Natural Language :: English
Classifier: Programming Language :: Python :: 3
Classifier: Programming Language :: Python :: 3.5
Classifier: Programming Language :: Python :: 3.6
Classifier: Programming Language :: Python :: 3.7
Classifier: Programming Language :: Python :: 3.8
License-File: LICENSE
License-File: AUTHORS.rst
Requires-Dist: django (<3.0)
Requires-Dist: django-environ (==0.7.0)
Requires-Dist: django-allauth (==0.45.0)
Requires-Dist: django-countries (==7.2.1)
Requires-Dist: django-treebeard (==4.5.1)
Requires-Dist: djangorestframework (==3.11.2)
Requires-Dist: Pillow (==7.1.1)
Requires-Dist: django-filter (==2.4.0)
Requires-Dist: pyjwt (==1.7.1)
Requires-Dist: Jinja2 (==3.0.2)
Requires-Dist: celery (==4.4.2)
Requires-Dist: django-filer (==2.0.2)
Requires-Dist: django-json-widget (==1.0.1)
Requires-Dist: django-sso-app (>=0.12.0)
